zvukogram/__init__.py
zvukogram/api.py
zvukogram/exceptions.py
zvukogram/models/__init__.py
zvukogram/models/audio.py
zvukogram/models/voice.py
zvukogram-1.0.1.dist-info/LICENSE
zvukogram-1.0.1.dist-info/METADATA
zvukogram-1.0.1.dist-info/WHEEL
zvukogram-1.0.1.dist-info/top_level.txt
zvukogram-1.0.1.dist-info/RECORD
