Metadata-Version: 2.1
Name: zvukogram
Version: 1.0.1
Summary: Asynchronous ZvukoGram API wrapper
Home-page: https://github.com/nikitalm8/zvukogram
Author: Nikita Minaev
Author-email: <nikita@minaev.su>
Project-URL: Homepage, https://github.com/nikitalm8/zvukogram
Project-URL: Bug Tracker, https://github.com/nikitalm8/zvukogram/issues
Project-URL: API Docs, https://zvukogram.com/node/api/
Keywords: python,zvukogram,payments,async,asyncio,aiohttp,pydantic
Classifier: Development Status :: 4 - Beta
Classifier: Intended Audience :: Developers
Classifier: Programming Language :: Python :: 3
Classifier: Operating System :: Unix
Classifier: Operating System :: MacOS :: MacOS X
Classifier: Operating System :: Microsoft :: Windows
License-File: LICENSE
Requires-Dist: aiohttp
Requires-Dist: pydantic
